MANIFEST.in
README.rst
TODO.txt
bootstrap.py
buildout.cfg
setup.py
buildout.d/base.cfg
buildout.d/development.cfg
buildout.d/versions.cfg
docs/HISTORY.txt
docs/LICENSE.GPL
docs/LICENSE.rst
docs/LICENSE.txt
src/Products/__init__.py
src/Products.MasterSelectWidget.egg-info/PKG-INFO
src/Products.MasterSelectWidget.egg-info/SOURCES.txt
src/Products.MasterSelectWidget.egg-info/dependency_links.txt
src/Products.MasterSelectWidget.egg-info/entry_points.txt
src/Products.MasterSelectWidget.egg-info/namespace_packages.txt
src/Products.MasterSelectWidget.egg-info/not-zip-safe
src/Products.MasterSelectWidget.egg-info/requires.txt
src/Products.MasterSelectWidget.egg-info/top_level.txt
src/Products/MasterSelectWidget/MasterBooleanWidget.py
src/Products/MasterSelectWidget/MasterMultiSelectWidget.py
src/Products/MasterSelectWidget/MasterSelectDemo.py
src/Products/MasterSelectWidget/MasterSelectWidget.py
src/Products/MasterSelectWidget/__init__.py
src/Products/MasterSelectWidget/browser.py
src/Products/MasterSelectWidget/config.py
src/Products/MasterSelectWidget/configure.zcml
src/Products/MasterSelectWidget/masterselect.js
src/Products/MasterSelectWidget/testing.py
src/Products/MasterSelectWidget/testing.zcml
src/Products/MasterSelectWidget/profiles/default/metadata.xml
src/Products/MasterSelectWidget/profiles/default/skins.xml
src/Products/MasterSelectWidget/profiles/demo/factorytool.xml
src/Products/MasterSelectWidget/profiles/demo/metadata.xml
src/Products/MasterSelectWidget/profiles/demo/types.xml
src/Products/MasterSelectWidget/profiles/demo/types/MasterSelectDemo.xml
src/Products/MasterSelectWidget/skins/masterselectwidget/masterboolean.pt
src/Products/MasterSelectWidget/skins/masterselectwidget/mastermultiselection.pt
src/Products/MasterSelectWidget/skins/masterselectwidget/masterselection.pt
src/Products/MasterSelectWidget/tests/__init__.py
src/Products/MasterSelectWidget/tests/test_robot.py
src/Products/MasterSelectWidget/tests/robot/.gitkeep
src/Products/MasterSelectWidget/tests/robot/test_selectwidget.robot