Metadata-Version: 1.0
Name: Products.MasterSelectWidget
Version: 0.4.8
Summary: An Archetypes widget that controls the vocabulary or display of otheer fields on an edit page
Home-page: http://plone.org/products/masterselectwidget/
Author: Plone Collective
Author-email: plone-developers@lists.sourceforge.net
License: BSD
Platform: UNKNOWN
Classifier: Framework :: Plone
Classifier: Programming Language :: Python
Classifier: Topic :: Software Development :: Libraries :: Python Modules
